{
    "type": "NeuralNetwork",
    "sizes": [
        4,
        4,
        8,
        1
    ],
    "layers": [
        {
            "weights": [],
            "biases": []
        },
        {
            "weights": [
                [
                    3.8228769302368164,
                    6.973735332489014,
                    8.152364730834961,
                    2.8855457305908203
                ],
                [
                    4.033811092376709,
                    -2.6714484691619873,
                    9.029168128967285,
                    -2.7431468963623047
                ],
                [
                    6.30551290512085,
                    6.6984710693359375,
                    2.507596731185913,
                    2.663740396499634
                ],
                [
                    3.4718432426452637,
                    6.850671768188477,
                    -0.21612222492694855,
                    7.350959300994873
                ]
            ],
            "biases": [
                -20.347278594970703,
                -2.0217015743255615,
                -5.1462483406066895,
                -8.607102394104004
            ]
        },
        {
            "weights": [
                [
                    -5.269539833068848,
                    -0.44647297263145447,
                    -0.42899760603904724,
                    -0.6441016793251038
                ],
                [
                    -5.268111228942871,
                    -0.44604599475860596,
                    -0.428524374961853,
                    -0.6442251801490784
                ],
                [
                    -5.201879978179932,
                    -0.4477023482322693,
                    -0.429307758808136,
                    -0.6452968120574951
                ],
                [
                    -5.253628730773926,
                    -0.44377097487449646,
                    -0.42698222398757935,
                    -0.6430649161338806
                ],
                [
                    -5.264575958251953,
                    -0.44642940163612366,
                    -0.42884981632232666,
                    -0.64438796043396
                ],
                [
                    -5.2518439292907715,
                    -0.4452895522117615,
                    -0.427344411611557,
                    -0.6443901658058167
                ],
                [
                    -5.250388145446777,
                    -0.445520281791687,
                    -0.42720717191696167,
                    -0.6449331045150757
                ],
                [
                    -5.2492499351501465,
                    -0.44561466574668884,
                    -0.4279685318470001,
                    -0.6441618800163269
                ]
            ],
            "biases": [
                -4.7693023681640625,
                -4.775157451629639,
                -4.772820472717285,
                -4.779580593109131,
                -4.768418312072754,
                -4.771556377410889,
                -4.772200584411621,
                -4.771427631378174
            ]
        },
        {
            "weights": [
                [
                    4.999416828155518,
                    5.02632474899292,
                    5.0192742347717285,
                    5.035268306732178,
                    4.994662284851074,
                    5.000067710876465,
                    5.005246162414551,
                    5.001870632171631
                ]
            ],
            "biases": [
                -0.35228461027145386
            ]
        }
    ],
    "inputLookup": null,
    "inputLookupLength": 0,
    "outputLookup": null,
    "outputLookupLength": 0,
    "options": {
        "inputSize": 0,
        "outputSize": 0,
        "binaryThresh": 0.5,
        "hiddenLayers": [
            4,
            8
        ]
    },
    "trainOpts": {
        "activation": "sigmoid",
        "iterations": 20000,
        "errorThresh": 0.005,
        "log": false,
        "logPeriod": 10,
        "leakyReluAlpha": 0.01,
        "learningRate": 0.3,
        "momentum": 0.1,
        "callbackPeriod": 10,
        "timeout": "Infinity",
        "beta1": 0.9,
        "beta2": 0.999,
        "epsilon": 1e-8
    }
}